llmjammer/__init__.py
llmjammer/__main__.py
llmjammer/cli.py
llmjammer/llmjammer.py
llmjammer/utils.py
llmjammer-0.0.2.dist-info/licenses/LICENSE
llmjammer-0.0.2.dist-info/METADATA
llmjammer-0.0.2.dist-info/WHEEL
llmjammer-0.0.2.dist-info/entry_points.txt
llmjammer-0.0.2.dist-info/top_level.txt
llmjammer-0.0.2.dist-info/RECORD
