Metadata-Version: 2.4
Name: llmjammer
Version: 0.0.2
Summary: A code obfuscator to confuse LLMs
Author-email: Eric Spencer <espencer2@luc.edu>
Maintainer-email: Eric Spencer <espencer2@luc.edu>
License: MIT
Project-URL: bugs, https://github.com/EricSpencer00/llmjammer/issues
Project-URL: changelog, https://github.com/EricSpencer00/llmjammer/blob/master/changelog.md
Project-URL: homepage, https://github.com/EricSpencer00/llmjammer
Classifier: Development Status :: 3 - Alpha
Classifier: Intended Audience :: Developers
Classifier: License :: OSI Approved :: MIT License
Classifier: Natural Language :: English
Classifier: Programming Language :: Python :: 3
Classifier: Programming Language :: Python :: 3.10
Classifier: Programming Language :: Python :: 3.11
Requires-Python: >=3.10
License-File: LICENSE
Requires-Dist: typer>=0.9.0
Requires-Dist: rich>=13.4.2
Requires-Dist: ast-comments>=1.0.1
Provides-Extra: test
Requires-Dist: coverage; extra == "test"
Requires-Dist: pytest; extra == "test"
Requires-Dist: ruff; extra == "test"
Requires-Dist: ty; extra == "test"
Requires-Dist: ipdb; extra == "test"
Dynamic: license-file
